RustCankaoshouceFix1/README.md
RustCankaoshouceFix1/__init__.py
RustCankaoshouceFix1/__main__.py
RustCankaoshouceFix1/file.epub
RustCankaoshouceFix1/index.html
RustCankaoshouceFix1/css/__init__.py
RustCankaoshouceFix1/css/annotations.css
RustCankaoshouceFix1/css/main.css
RustCankaoshouceFix1/css/normalize.css
RustCankaoshouceFix1/css/popup.css
RustCankaoshouceFix1/font/__init__.py
RustCankaoshouceFix1/font/fontello.eot
RustCankaoshouceFix1/font/fontello.svg
RustCankaoshouceFix1/font/fontello.ttf
RustCankaoshouceFix1/font/fontello.woff
RustCankaoshouceFix1/img/__init__.py
RustCankaoshouceFix1/img/annotator-glyph-sprite.png
RustCankaoshouceFix1/img/annotator-icon-sprite.png
RustCankaoshouceFix1/img/apple-touch-icon.png
RustCankaoshouceFix1/img/cancelfullscreen.png
RustCankaoshouceFix1/img/close.png
RustCankaoshouceFix1/img/fullscreen.png
RustCankaoshouceFix1/img/loader.gif
RustCankaoshouceFix1/img/menu-icon.png
RustCankaoshouceFix1/img/save.png
RustCankaoshouceFix1/img/saved.png
RustCankaoshouceFix1/img/settings-s.png
RustCankaoshouceFix1/img/settings.png
RustCankaoshouceFix1/img/star.png
RustCankaoshouceFix1/js/__init__.py
RustCankaoshouceFix1/js/epub.js
RustCankaoshouceFix1/js/epub.min.js
RustCankaoshouceFix1/js/epub.min.map
RustCankaoshouceFix1/js/hooks.min.js
RustCankaoshouceFix1/js/hooks.min.map
RustCankaoshouceFix1/js/reader.js
RustCankaoshouceFix1/js/reader.js.map
RustCankaoshouceFix1/js/reader.min.js
RustCankaoshouceFix1/js/reader.min.map
RustCankaoshouceFix1/js/hooks/__init__.py
RustCankaoshouceFix1/js/hooks/extensions/__init__.py
RustCankaoshouceFix1/js/hooks/extensions/highlight.js
RustCankaoshouceFix1/js/libs/__init__.py
RustCankaoshouceFix1/js/libs/jquery.min.js
RustCankaoshouceFix1/js/libs/localforage.min.js
RustCankaoshouceFix1/js/libs/screenfull.js
RustCankaoshouceFix1/js/libs/screenfull.min.js
RustCankaoshouceFix1/js/libs/zip.min.js
RustCankaoshouceFix1/js/plugins/__init__.py
RustCankaoshouceFix1/js/plugins/hypothesis.js
rust_cankaoshouce_fix1-2025.3.24.0.dist-info/METADATA
rust_cankaoshouce_fix1-2025.3.24.0.dist-info/WHEEL
rust_cankaoshouce_fix1-2025.3.24.0.dist-info/entry_points.txt
rust_cankaoshouce_fix1-2025.3.24.0.dist-info/top_level.txt
rust_cankaoshouce_fix1-2025.3.24.0.dist-info/RECORD
